BottleCasBridge/CasTicketManager.py
BottleCasBridge/URNmanager.py
BottleCasBridge/__init__.py
BottleCasBridge/casSaml_request.py
BottleCasBridge/cas_response.py
BottleCasBridge/cas_server.py
BottleCasBridge/views/__init__.py
BottleCasBridge/views/base.html
BottleCasBridge/views/cas_loggedin.html
BottleCasBridge/views/cas_loggedout.html
BottleCasBridge/views/v2_auth_failure.xml
BottleCasBridge/views/v2_auth_success.xml
BottleCasBridge/views/v2_proxy_failure.xml
BottleCasBridge/views/v2_proxy_success.xml
BottleCasBridge/views/v3_cas_saml_error.xml
BottleCasBridge/views/v3_cas_saml_success.xml
BottleCasBridge/views/css/__init__.py
BottleCasBridge/views/css/proj.css
BottleCasBridge/views/css/spinner.css
BottleCasBridge-21.9.21.data/data/example/cas_saml_bridge.py
BottleCasBridge-21.9.21.data/data/example/sample_config.py
BottleCasBridge-21.9.21.dist-info/METADATA
BottleCasBridge-21.9.21.dist-info/WHEEL
BottleCasBridge-21.9.21.dist-info/top_level.txt
BottleCasBridge-21.9.21.dist-info/RECORD
