Metadata-Version: 2.1
Name: BottleCasBridge
Version: 21.9.21
Summary: SAML-based CAS Bridge using Bottle
Home-page: https://github.com/Glocktober/BottleCasBridge
Author: gunville
Author-email: rk13088@yahoo.com
License: UNKNOWN
Project-URL: repo, https://github.com/Glocktober/BottleCasBridge
Project-URL: overview, https://github.com/Glocktober/BottleCasBridge/blob/main/README.md
Keywords: 'bottle CAS SAML bridge'
Platform: UNKNOWN
Classifier: Programming Language :: Python :: 3
Classifier: License :: OSI Approved :: MIT License
Classifier: Operating System :: OS Independent
Classifier: Framework :: Bottle
Requires-Python: >=3.6
Requires-Dist: bottle
Requires-Dist: BottleSessions
Requires-Dist: BottleSaml
Requires-Dist: defusedxml
Requires-Dist: jinja2
Requires-Dist: minisaml
Requires-Dist: requests
